katmlutils/__init__.py
katmlutils/utils.py
katmlutils-0.1.3.dist-info/METADATA
katmlutils-0.1.3.dist-info/WHEEL
katmlutils-0.1.3.dist-info/entry_points.txt
katmlutils-0.1.3.dist-info/licenses/LICENSE
katmlutils-0.1.3.dist-info/RECORD
