Metadata-Version: 2.4
Name: katmlutils
Version: 0.1.3
Summary:  This is a package that keeps all the Machine learning Utils in the Software Team.
Author-email: SARAO MLOps <saraomlops@gmail.com>
License: MIT
License-File: LICENSE
Keywords: machine learning,utils
Classifier: License :: OSI Approved :: MIT License
Classifier: Operating System :: OS Independent
Classifier: Programming Language :: Python :: 3
Requires-Python: >=3.9
Requires-Dist: lst-pressure==1.8.6
